[
  {
    "id": "chal_001",
    "conceptId": "cs_002",
    "difficulty": "easy",
    "source": "preauthored",
    "createdAt": 1714425600000,
    "content": {
      "question": "What does a function do?",
      "options": [
        "Stores a single value",
        "Executes a reusable block of code",
        "Repeats code multiple times",
        "Declares a variable"
      ],
      "correctIndex": 1,
      "explanation": "A function is a reusable block of code that performs a specific task."
    },
    "correctAnswer": "1",
    "metadata": {
      "gameType": "challenge",
      "requiredFields": ["question", "options", "correctIndex"],
      "expectedDuration": 20000
    }
  },
  {
    "id": "chal_002",
    "conceptId": "math_002",
    "difficulty": "medium",
    "source": "preauthored",
    "createdAt": 1714425600000,
    "content": {
      "question": "What is the prime factorization of 24?",
      "options": [
        "2 × 3 × 4",
        "2² × 3",
        "2³ × 3",
        "2 × 12"
      ],
      "correctIndex": 2,
      "explanation": "24 = 8 × 3 = 2³ × 3. Prime factors are only the prime numbers."
    },
    "correctAnswer": "2",
    "metadata": {
      "gameType": "challenge",
      "requiredFields": ["question", "options", "correctIndex"],
      "expectedDuration": 25000
    }
  },
  {
    "id": "chal_003",
    "conceptId": "dsa_002",
    "difficulty": "hard",
    "source": "preauthored",
    "createdAt": 1714425600000,
    "content": {
      "question": "What is the time complexity of binary search?",
      "options": [
        "O(n)",
        "O(log n)",
        "O(n²)",
        "O(1)"
      ],
      "correctIndex": 1,
      "explanation": "Binary search eliminates half the search space with each comparison, giving O(log n) complexity."
    },
    "correctAnswer": "1",
    "metadata": {
      "gameType": "challenge",
      "requiredFields": ["question", "options", "correctIndex"],
      "expectedDuration": 20000
    }
  },
  {
    "id": "chal_004",
    "conceptId": "cs_003",
    "difficulty": "easy",
    "source": "preauthored",
    "createdAt": 1714425600000,
    "content": {
      "question": "Which data structure uses LIFO principle?",
      "options": [
        "Queue",
        "Deque",
        "Stack",
        "Heap"
      ],
      "correctIndex": 2,
      "explanation": "A Stack follows Last-In-First-Out (LIFO) principle where the last added element is removed first."
    },
    "correctAnswer": "2",
    "metadata": {
      "gameType": "challenge",
      "requiredFields": ["question", "options", "correctIndex"],
      "expectedDuration": 15000
    }
  },
  {
    "id": "chal_005",
    "conceptId": "physics_002",
    "difficulty": "medium",
    "source": "preauthored",
    "createdAt": 1714425600000,
    "content": {
      "question": "If an object moves at constant velocity, what is the net force?",
      "options": [
        "Maximum force",
        "Zero",
        "Equal to mass",
        "Equal to weight"
      ],
      "correctIndex": 1,
      "explanation": "By Newton's first law, constant velocity means no acceleration, so net force = 0."
    },
    "correctAnswer": "1",
    "metadata": {
      "gameType": "challenge",
      "requiredFields": ["question", "options", "correctIndex"],
      "expectedDuration": 20000
    }
  }
]
