[
  {
    "id": "mem_001",
    "conceptId": "cs_001",
    "difficulty": "easy",
    "source": "preauthored",
    "createdAt": 1714425600000,
    "content": {
      "items": [
        { "name": "Variable", "definition": "Named storage location" },
        { "name": "Function", "definition": "Reusable block of code" },
        { "name": "Loop", "definition": "Repeated execution" }
      ]
    },
    "metadata": {
      "gameType": "memory",
      "requiredFields": ["items"],
      "expectedDuration": 30000
    }
  },
  {
    "id": "mem_002",
    "conceptId": "math_001",
    "difficulty": "medium",
    "source": "preauthored",
    "createdAt": 1714425600000,
    "content": {
      "items": [
        { "name": "Prime Number", "definition": "Only divisible by 1 and itself" },
        { "name": "Composite", "definition": "Has more than 2 factors" },
        { "name": "Factor", "definition": "Number that divides evenly" },
        { "name": "Multiple", "definition": "Product of a number with integer" }
      ]
    },
    "metadata": {
      "gameType": "memory",
      "requiredFields": ["items"],
      "expectedDuration": 45000
    }
  },
  {
    "id": "mem_003",
    "conceptId": "dsa_001",
    "difficulty": "medium",
    "source": "preauthored",
    "createdAt": 1714425600000,
    "content": {
      "items": [
        { "name": "Array", "definition": "Ordered collection with fixed size" },
        { "name": "Linked List", "definition": "Nodes connected via pointers" },
        { "name": "Stack", "definition": "LIFO - Last In First Out" },
        { "name": "Queue", "definition": "FIFO - First In First Out" },
        { "name": "Hash Table", "definition": "Key-value pairs with O(1) lookup" }
      ]
    },
    "metadata": {
      "gameType": "memory",
      "requiredFields": ["items"],
      "expectedDuration": 60000
    }
  },
  {
    "id": "mem_004",
    "conceptId": "physics_001",
    "difficulty": "hard",
    "source": "preauthored",
    "createdAt": 1714425600000,
    "content": {
      "items": [
        { "name": "Force", "definition": "F = ma (pushes or pulls)" },
        { "name": "Velocity", "definition": "Rate of change of position" },
        { "name": "Acceleration", "definition": "Rate of change of velocity" },
        { "name": "Momentum", "definition": "p = mv (mass × velocity)" },
        { "name": "Energy", "definition": "Capacity to do work" },
        { "name": "Power", "definition": "Rate of energy transfer" }
      ]
    },
    "metadata": {
      "gameType": "memory",
      "requiredFields": ["items"],
      "expectedDuration": 90000
    }
  }
]
